{
    "type": "historical",
    "source": "roget",
    "category": "SPECIAL FORM",
    "description": "Roget's Thesaurus -  / FORM / SPECIAL FORM",
    "license": "Public Domain",
    "version": "1.0",
    "citation": "Roget, P. M. (1852). Thesaurus of English Words and Phrases. Longman, Brown, Green, and Longmans.",
    "total_words": 19,
    "words": [
        "angular",
        "angularity",
        "bend",
        "bowed",
        "circularity",
        "convoluted",
        "curvature",
        "curved",
        "cycloidal",
        "polygonal",
        "rotund",
        "rotundity",
        "round",
        "roundness",
        "straight",
        "straightness",
        "twisted",
        "virgate",
        "winding"
    ]
}