{
    "type": "historical",
    "source": "roget",
    "category": "[Motion in a continued circle.] Rotation.",
    "description": "Roget's Thesaurus - II / II. DIMENSIONS / [Motion in a continued circle.] Rotation. ",
    "license": "Public Domain",
    "version": "1.0",
    "citation": "Roget, P. M. (1852). Thesaurus of English Words and Phrases. Longman, Brown, Green, and Longmans.",
    "total_words": 12,
    "words": [
        "circumrotatory",
        "circumvolve",
        "head over heels",
        "like a horse in a mill",
        "revolve",
        "roll along",
        "rotary",
        "rotate",
        "rotating",
        "round and round",
        "spin",
        "turn round"
    ]
}