{
    "type": "historical",
    "source": "roget",
    "category": "Hardness.",
    "description": "Roget's Thesaurus - III / II. DIMENSIONS / Hardness. ",
    "license": "Public Domain",
    "version": "1.0",
    "citation": "Roget, P. M. (1852). Thesaurus of English Words and Phrases. Longman, Brown, Green, and Longmans.",
    "total_words": 14,
    "words": [
        "firm",
        "hard",
        "harden",
        "indurate",
        "petrify",
        "render hard",
        "rigid",
        "starch",
        "starched",
        "stark",
        "stiff",
        "stiffen",
        "stubborn",
        "temper"
    ]
}